ofdlib.py
ofdlib-0.0.1.dist-info/WHEEL
ofdlib-0.0.1.dist-info/METADATA
ofdlib-0.0.1.dist-info/RECORD
